yta_video_moviepy/__init__.py
yta_video_moviepy/frame/__init__.py
yta_video_moviepy/frame/extractor.py
yta_video_moviepy/generator.py
yta_video_moviepy/utils.py
yta_video_moviepy/writer.py
yta_video_moviepy-0.0.10.dist-info/licenses/LICENSE
yta_video_moviepy-0.0.10.dist-info/METADATA
yta_video_moviepy-0.0.10.dist-info/WHEEL
yta_video_moviepy-0.0.10.dist-info/RECORD
