Metadata-Version: 2.4
Name: yta-video-moviepy
Version: 0.0.10
Summary: Youtube Autonomous Video Moviepy Module
License-File: LICENSE
Author: danialcala94
Author-email: danielalcalavalera@gmail.com
Requires-Python: ==3.9
Classifier: Programming Language :: Python :: 3
Classifier: Programming Language :: Python :: 3.9
Requires-Dist: moviepy (>=2.0.0,<3.0.0)
Requires-Dist: yta_colors (>=0.0.1,<1.0.0)
Requires-Dist: yta_constants (>=0.0.1,<1.0.0)
Requires-Dist: yta_numpy (>=0.0.1,<1.0.0)
Requires-Dist: yta_programming (>=0.0.1,<1.0.0)
Requires-Dist: yta_validation (>=0.0.1,<1.0.0)
Requires-Dist: yta_video_frame_time (>=0.0.1,<1.0.0)
